{
  "updated": "2026-06-17",
  "mode": "soft",
  "count": 55,
  "sites": [
    {
      "domain": "aboutyou.de",
      "status": "ok",
      "score": 100,
      "grade": "A",
      "fails": 0,
      "passes": 3,
      "top_issue": null,
      "error_code": null,
      "scanned_at": 1781725290017
    },
    {
      "domain": "alltricks.fr",
      "status": "ok",
      "score": 100,
      "grade": "A",
      "fails": 0,
      "passes": 3,
      "top_issue": null,
      "error_code": null,
      "scanned_at": 1781725267216
    },
    {
      "domain": "asambeauty.com",
      "status": "ok",
      "score": 100,
      "grade": "A",
      "fails": 0,
      "passes": 3,
      "top_issue": null,
      "error_code": null,
      "scanned_at": 1781725256367
    },
    {
      "domain": "avocadostore.de",
      "status": "ok",
      "score": 100,
      "grade": "A",
      "fails": 0,
      "passes": 3,
      "top_issue": null,
      "error_code": null,
      "scanned_at": 1781725255661
    },
    {
      "domain": "bangerhead.com",
      "status": "ok",
      "score": 100,
      "grade": "A",
      "fails": 0,
      "passes": 3,
      "top_issue": null,
      "error_code": null,
      "scanned_at": 1781725287237
    },
    {
      "domain": "baur.de",
      "status": "ok",
      "score": 100,
      "grade": "A",
      "fails": 0,
      "passes": 3,
      "top_issue": null,
      "error_code": null,
      "scanned_at": 1781725252202
    },
    {
      "domain": "bonprix.de",
      "status": "ok",
      "score": 100,
      "grade": "A",
      "fails": 0,
      "passes": 3,
      "top_issue": null,
      "error_code": null,
      "scanned_at": 1781725252202
    },
    {
      "domain": "boohoo.com",
      "status": "ok",
      "score": 100,
      "grade": "A",
      "fails": 0,
      "passes": 3,
      "top_issue": null,
      "error_code": null,
      "scanned_at": 1781725288908
    },
    {
      "domain": "bottegaverde.it",
      "status": "ok",
      "score": 100,
      "grade": "A",
      "fails": 0,
      "passes": 3,
      "top_issue": null,
      "error_code": null,
      "scanned_at": 1781725281397
    },
    {
      "domain": "breuninger.com",
      "status": "ok",
      "score": 100,
      "grade": "A",
      "fails": 0,
      "passes": 3,
      "top_issue": null,
      "error_code": null,
      "scanned_at": 1781725254954
    },
    {
      "domain": "cdiscount.com",
      "status": "ok",
      "score": 100,
      "grade": "A",
      "fails": 0,
      "passes": 3,
      "top_issue": null,
      "error_code": null,
      "scanned_at": 1781725270962
    },
    {
      "domain": "charlottetilbury.com",
      "status": "ok",
      "score": 100,
      "grade": "A",
      "fails": 0,
      "passes": 3,
      "top_issue": null,
      "error_code": null,
      "scanned_at": 1781725288689
    },
    {
      "domain": "cultbeauty.co.uk",
      "status": "ok",
      "score": 100,
      "grade": "A",
      "fails": 0,
      "passes": 3,
      "top_issue": null,
      "error_code": null,
      "scanned_at": 1781725287879
    },
    {
      "domain": "eataly.com",
      "status": "ok",
      "score": 100,
      "grade": "A",
      "fails": 0,
      "passes": 3,
      "top_issue": null,
      "error_code": null,
      "scanned_at": 1781725281056
    },
    {
      "domain": "ellos.se",
      "status": "ok",
      "score": 100,
      "grade": "A",
      "fails": 0,
      "passes": 3,
      "top_issue": null,
      "error_code": null,
      "scanned_at": 1781725285978
    },
    {
      "domain": "fnac.com",
      "status": "ok",
      "score": 100,
      "grade": "A",
      "fails": 0,
      "passes": 3,
      "top_issue": null,
      "error_code": null,
      "scanned_at": 1781725290089
    },
    {
      "domain": "gymshark.com",
      "status": "ok",
      "score": 100,
      "grade": "A",
      "fails": 0,
      "passes": 3,
      "top_issue": null,
      "error_code": null,
      "scanned_at": 1781725288609
    },
    {
      "domain": "juniqe.com",
      "status": "ok",
      "score": 100,
      "grade": "A",
      "fails": 0,
      "passes": 3,
      "top_issue": null,
      "error_code": null,
      "scanned_at": 1781725257419
    },
    {
      "domain": "lookfantastic.com",
      "status": "ok",
      "score": 100,
      "grade": "A",
      "fails": 0,
      "passes": 3,
      "top_issue": null,
      "error_code": null,
      "scanned_at": 1781725287543
    },
    {
      "domain": "manufactum.de",
      "status": "ok",
      "score": 100,
      "grade": "A",
      "fails": 0,
      "passes": 3,
      "top_issue": null,
      "error_code": null,
      "scanned_at": 1781725255175
    },
    {
      "domain": "mytoys.de",
      "status": "ok",
      "score": 100,
      "grade": "A",
      "fails": 0,
      "passes": 3,
      "top_issue": null,
      "error_code": null,
      "scanned_at": 1781725257186
    },
    {
      "domain": "na-kd.com",
      "status": "ok",
      "score": 100,
      "grade": "A",
      "fails": 0,
      "passes": 3,
      "top_issue": null,
      "error_code": null,
      "scanned_at": 1781725286369
    },
    {
      "domain": "nelly.com",
      "status": "ok",
      "score": 100,
      "grade": "A",
      "fails": 0,
      "passes": 3,
      "top_issue": null,
      "error_code": null,
      "scanned_at": 1781725285837
    },
    {
      "domain": "nocibe.fr",
      "status": "ok",
      "score": 100,
      "grade": "A",
      "fails": 0,
      "passes": 3,
      "top_issue": null,
      "error_code": null,
      "scanned_at": 1781725260113
    },
    {
      "domain": "privalia.com",
      "status": "ok",
      "score": 100,
      "grade": "A",
      "fails": 0,
      "passes": 3,
      "top_issue": null,
      "error_code": null,
      "scanned_at": 1781725282997
    },
    {
      "domain": "tchibo.de",
      "status": "ok",
      "score": 100,
      "grade": "A",
      "fails": 0,
      "passes": 3,
      "top_issue": null,
      "error_code": null,
      "scanned_at": 1781725252202
    },
    {
      "domain": "zalando.de",
      "status": "ok",
      "score": 100,
      "grade": "A",
      "fails": 0,
      "passes": 3,
      "top_issue": null,
      "error_code": null,
      "scanned_at": 1781725289214
    },
    {
      "domain": "bergfreunde.de",
      "status": "ok",
      "score": 67,
      "grade": "C",
      "fails": 1,
      "passes": 2,
      "top_issue": "Cookie notice",
      "error_code": null,
      "scanned_at": 1781725256806
    },
    {
      "domain": "flaconi.de",
      "status": "ok",
      "score": 67,
      "grade": "C",
      "fails": 1,
      "passes": 2,
      "top_issue": "Cookie notice",
      "error_code": null,
      "scanned_at": 1781725252201
    },
    {
      "domain": "home24.de",
      "status": "ok",
      "score": 67,
      "grade": "C",
      "fails": 1,
      "passes": 2,
      "top_issue": "Cookie notice",
      "error_code": null,
      "scanned_at": 1781725254551
    },
    {
      "domain": "laredoute.fr",
      "status": "ok",
      "score": 67,
      "grade": "C",
      "fails": 1,
      "passes": 2,
      "top_issue": "Cookie notice",
      "error_code": null,
      "scanned_at": 1781725258370
    },
    {
      "domain": "notino.de",
      "status": "ok",
      "score": 67,
      "grade": "C",
      "fails": 1,
      "passes": 2,
      "top_issue": "Cookie notice",
      "error_code": null,
      "scanned_at": 1781725252197
    },
    {
      "domain": "reuter.de",
      "status": "ok",
      "score": 67,
      "grade": "C",
      "fails": 1,
      "passes": 2,
      "top_issue": "Cookie notice",
      "error_code": null,
      "scanned_at": 1781725253954
    },
    {
      "domain": "sezane.com",
      "status": "ok",
      "score": 67,
      "grade": "C",
      "fails": 1,
      "passes": 2,
      "top_issue": "Cookie notice",
      "error_code": null,
      "scanned_at": 1781725259867
    },
    {
      "domain": "smallable.com",
      "status": "ok",
      "score": 67,
      "grade": "C",
      "fails": 1,
      "passes": 2,
      "top_issue": "Cookie notice",
      "error_code": null,
      "scanned_at": 1781725263235
    },
    {
      "domain": null,
      "hidden": true,
      "status": "ok",
      "score": 33,
      "grade": "F",
      "fails": 2,
      "passes": 1,
      "top_issue": null,
      "error_code": null,
      "scanned_at": 1781725284975
    },
    {
      "domain": null,
      "hidden": true,
      "status": "ok",
      "score": 33,
      "grade": "F",
      "fails": 2,
      "passes": 1,
      "top_issue": null,
      "error_code": null,
      "scanned_at": 1781725254849
    },
    {
      "domain": null,
      "hidden": true,
      "status": "ok",
      "score": 33,
      "grade": "F",
      "fails": 2,
      "passes": 1,
      "top_issue": null,
      "error_code": null,
      "scanned_at": 1781725278458
    },
    {
      "domain": null,
      "hidden": true,
      "status": "ok",
      "score": 33,
      "grade": "F",
      "fails": 2,
      "passes": 1,
      "top_issue": null,
      "error_code": null,
      "scanned_at": 1781725280997
    },
    {
      "domain": null,
      "hidden": true,
      "status": "ok",
      "score": 33,
      "grade": "F",
      "fails": 2,
      "passes": 1,
      "top_issue": null,
      "error_code": null,
      "scanned_at": 1781725284355
    },
    {
      "domain": null,
      "hidden": true,
      "status": "ok",
      "score": 33,
      "grade": "F",
      "fails": 2,
      "passes": 1,
      "top_issue": null,
      "error_code": null,
      "scanned_at": 1781725282262
    },
    {
      "domain": null,
      "hidden": true,
      "status": "ok",
      "score": 33,
      "grade": "F",
      "fails": 2,
      "passes": 1,
      "top_issue": null,
      "error_code": null,
      "scanned_at": 1781725278345
    },
    {
      "domain": null,
      "hidden": true,
      "status": "ok",
      "score": 33,
      "grade": "F",
      "fails": 2,
      "passes": 1,
      "top_issue": null,
      "error_code": null,
      "scanned_at": 1781725259140
    },
    {
      "domain": null,
      "hidden": true,
      "status": "ok",
      "score": 33,
      "grade": "F",
      "fails": 2,
      "passes": 1,
      "top_issue": null,
      "error_code": null,
      "scanned_at": 1781725282859
    },
    {
      "domain": null,
      "hidden": true,
      "status": "ok",
      "score": 33,
      "grade": "F",
      "fails": 2,
      "passes": 1,
      "top_issue": null,
      "error_code": null,
      "scanned_at": 1781725259292
    },
    {
      "domain": null,
      "hidden": true,
      "status": "ok",
      "score": 33,
      "grade": "F",
      "fails": 2,
      "passes": 1,
      "top_issue": null,
      "error_code": null,
      "scanned_at": 1781725277949
    },
    {
      "domain": null,
      "hidden": true,
      "status": "ok",
      "score": 33,
      "grade": "F",
      "fails": 2,
      "passes": 1,
      "top_issue": null,
      "error_code": null,
      "scanned_at": 1781725280575
    },
    {
      "domain": null,
      "hidden": true,
      "status": "ok",
      "score": 0,
      "grade": "F",
      "fails": 3,
      "passes": 0,
      "top_issue": null,
      "error_code": null,
      "scanned_at": 1781725285083
    },
    {
      "domain": null,
      "hidden": true,
      "status": "ok",
      "score": 0,
      "grade": "F",
      "fails": 3,
      "passes": 0,
      "top_issue": null,
      "error_code": null,
      "scanned_at": 1781725286440
    },
    {
      "domain": null,
      "hidden": true,
      "status": "ok",
      "score": 0,
      "grade": "F",
      "fails": 3,
      "passes": 0,
      "top_issue": null,
      "error_code": null,
      "scanned_at": 1781725278855
    },
    {
      "domain": null,
      "hidden": true,
      "status": "ok",
      "score": 0,
      "grade": "F",
      "fails": 3,
      "passes": 0,
      "top_issue": null,
      "error_code": null,
      "scanned_at": 1781725282835
    },
    {
      "domain": null,
      "hidden": true,
      "status": "ok",
      "score": 0,
      "grade": "F",
      "fails": 3,
      "passes": 0,
      "top_issue": null,
      "error_code": null,
      "scanned_at": 1781725260472
    },
    {
      "domain": null,
      "hidden": true,
      "status": "ok",
      "score": 0,
      "grade": "F",
      "fails": 3,
      "passes": 0,
      "top_issue": null,
      "error_code": null,
      "scanned_at": 1781725287002
    },
    {
      "domain": null,
      "hidden": true,
      "status": "ok",
      "score": 0,
      "grade": "F",
      "fails": 3,
      "passes": 0,
      "top_issue": null,
      "error_code": null,
      "scanned_at": 1781725280439
    },
    {
      "domain": null,
      "hidden": true,
      "status": "ok",
      "score": 0,
      "grade": "F",
      "fails": 3,
      "passes": 0,
      "top_issue": null,
      "error_code": null,
      "scanned_at": 1781725285380
    },
    {
      "domain": "made-in-design.com",
      "status": "error",
      "score": null,
      "grade": "—",
      "fails": null,
      "passes": null,
      "top_issue": null,
      "error_code": "network",
      "scanned_at": 1781725265646
    },
    {
      "domain": "perfumeriasprimor.com",
      "status": "error",
      "score": null,
      "grade": "—",
      "fails": null,
      "passes": null,
      "top_issue": null,
      "error_code": "dns",
      "scanned_at": 1781725284143
    }
  ]
}